tqsdk_zq_pgserver/__init__.py
tqsdk_zq_pgserver/__version__.py
tqsdk_zq_pgserver-1.0.0.dist-info/METADATA
tqsdk_zq_pgserver-1.0.0.dist-info/WHEEL
tqsdk_zq_pgserver-1.0.0.dist-info/top_level.txt
tqsdk_zq_pgserver-1.0.0.dist-info/RECORD
