Metadata-Version: 2.1
Name: tqsdk-zq-pgserver
Version: 1.0.0
Summary: TianQin SDK - zq_pgserver lib
Home-page: https://www.shinnytech.com/tqsdk
Author: TianQin
Author-email: tianqincn@gmail.com
License: UNKNOWN
Platform: UNKNOWN
Requires-Python: >=3
